apycalc/__init__.py
apycalc/__main__.py
apycalc/cli.py
apycalc-2.1.0.dist-info/licenses/LICENSE
apycalc-2.1.0.dist-info/METADATA
apycalc-2.1.0.dist-info/WHEEL
apycalc-2.1.0.dist-info/entry_points.txt
apycalc-2.1.0.dist-info/top_level.txt
apycalc-2.1.0.dist-info/RECORD
