Metadata-Version: 2.4
Name: apycalc
Version: 2.1.0
Summary: APY trend calculator with configurable Moving Average
Home-page: https://github.com/dmotte/apycalc
Author: dmotte
License: MIT
Keywords: calculator csv command percentage value yield average percent moving return yearly invest annual apy apycalc
Classifier: Intended Audience :: End Users/Desktop
Classifier: Environment :: Console
Classifier: Natural Language :: English
Classifier: License :: OSI Approved :: MIT License
Classifier: Programming Language :: Python
Classifier: Programming Language :: Python :: 3
Classifier: Programming Language :: Python :: 3 :: Only
Classifier: Programming Language :: Python :: 3.10
Classifier: Topic :: Terminals
Classifier: Topic :: Utilities
Requires-Python: >=3.10.12
License-File: LICENSE
Dynamic: license-file
